Step2/Not/not_gate.v
`ifndef NOT_GATE_V
`define NOT_GATE_V

module not_gate (Y, A);
    output [3:0] Y;  // 4-bit output
    input  [3:0] A;  // 4-bit input
    assign Y = !A; 
endmodule

`endif

Step2/Not/not_tb.v
`timescale 1ns / 1ns
`include "not_gate.v"

module not_tb;

reg [3:0]A;
wire [3:0]Y;

not_gate uut(Y, A);

integer i;  // Loop variable
initial begin

    $dumpfile("not_tb.vcd");//holds output waveform
    $dumpvars(0, not_tb);

    // Loop through all 16 combinations of 4-bit input
    for (i = 0; i < 16; i = i + 1) begin
        A = i;  // Assign binary value of i to A
        #10;    // Wait for 10 time units
    end

    
    $display("Testing not");

end

endmodule

Step2/Not/not_tb.vcd
$date
	Thu Oct 24 14:50:43 2024
$end
$version
	Icarus Verilog
$end
$timescale
	1ns
$end
$scope module not_tb $end
$var wire 4 ! Y [3:0] $end
$var reg 4 " A [3:0] $end
$var integer 32 # i [31:0] $end
$scope module uut $end
$var wire 4 $ A [3:0] $end
$var wire 4 % Y [3:0] $end
$upscope $end
$upscope $end
$enddefinitions $end
$comment Show the parameter values. $end
$dumpall
$end
#0
$dumpvars
b1 %
b0 $
b0 #
b0 "
b1 !
$end
#10
b0 !
b0 %
b1 "
b1 $
b1 #
#20
b10 "
b10 $
b10 #
#30
b11 "
b11 $
b11 #
#40
b100 "
b100 $
b100 #
#50
b101 "
b101 $
b101 #
#60
b110 "
b110 $
b110 #
#70
b111 "
b111 $
b111 #
#80
b1000 "
b1000 $
b1000 #
#90
b1001 "
b1001 $
b1001 #
#100
b1010 "
b1010 $
b1010 #
#110
b1011 "
b1011 $
b1011 #
#120
b1100 "
b1100 $
b1100 #
#130
b1101 "
b1101 $
b1101 #
#140
b1110 "
b1110 $
b1110 #
#150
b1111 "
b1111 $
b1111 #
#160
b10000 #
