Step3/alu.v
`ifndef ALU_V
`define ALU_V

module addition (
    input [3:0] A,         // 4-bit input A
    input [3:0] B,         // 4-bit input B
    input carry_in,        // 1-bit carry in
    output [3:0] Sum,      // 4-bit sum output
    output carry_out       // 1-bit carry out
);

    wire [4:0] full_sum;   // 5-bit sum to accommodate carry-out

    // Perform the addition with carry_in
    assign full_sum = A + B + carry_in;
    
    // Assign the lower 4 bits of the sum to the Sum output
    assign Sum = full_sum[3:0];
    
    // The 5th bit is the carry_out
    assign carry_out = full_sum[4];

endmodule

module subtraction (Y, A, B);
    output [3:0] Y;  // 4-bit output
    input  [3:0] A;  // 4-bit input A
    input  [3:0] B;  // 4-bit input B

    assign Y = A - B;  // Perform 4-bit subtraction

endmodule

module multiplication (
    input [3:0] A, B,   
    output [3:0] product_low,   // Lower 4 bits of the product
    output [3:0] product_high   // Upper 4 bits of the product
);
    wire [7:0] full_product;    // 8-bit wire to hold the full product
    
    assign full_product = A * B;
    assign product_low = full_product[3:0];   // Lower 4 bits
    assign product_high = full_product[7:4];  // Upper 4 bits
endmodule

module division (
    input [3:0] dividend,
    input [3:0] divisor,
    output reg [3:0] quotient,
    output reg [3:0] remainder,
    output reg valid
);
    reg [3:0] temp_dividend;
    reg [3:0] temp_quotient;
    
    integer i;

    always @(*) begin
        quotient = 4'b0000;
        remainder = 4'b0000;
        valid = 1'b0;

        if (divisor == 0) begin
            valid = 1'b0; 
            quotient = 4'b0000;
            remainder = dividend; 
        end else begin
            temp_dividend = dividend;
            temp_quotient = 4'b0000;

            for (i = 3; i >= 0; i = i - 1) begin
                temp_quotient = {temp_quotient[2:0], temp_dividend[3]};
                temp_dividend = {temp_dividend[2:0], 1'b0};

                //if (temp_quotient >= divisor) begin
                //    temp_quotient = temp_quotient - divisor;
                //    dividend[i:i] = 1'b1;
                //    end
            end

            quotient = temp_quotient;
            remainder = dividend;
            valid = 1'b1;
        end
    end
endmodule

`ifndef ALU_V
`define ALU_V

module alu (
    input [3:0] A, B,       // 4-bit inputs
    input carry_in,         // Carry input for addition
    input [1:0] shift_amt,  // 2-bit shift amount (unused in this case)
    input shift_dir,        // Shift direction (unused in this case)
    input [3:0] opcode,     // 4-bit control signal
    output reg [3:0] Y,     // 4-bit result output (this is a reg)
    output reg carry_out,   // Carry-out for addition (this is a reg)
    output reg valid_div,   // Valid flag for division (this is a reg)
    output reg [3:0] remainder, // Remainder from division (this is a reg)
    output reg [3:0] product_low, // Multiplication low part (this is a reg)
    output reg [3:0] product_high // Multiplication high part (this is a reg)
);

    // Intermediate wires for all module outputs
    wire [3:0] arithmetic_out;
    wire [3:0] quotient_out, remainder_out;
    wire add_carry_out;

    // Instantiate Arithmetic Modules
    addition u_add (.A(A), .B(B), .carry_in(carry_in), .Sum(arithmetic_out), .carry_out(add_carry_out));
    subtraction u_sub (.Y(arithmetic_out), .A(A), .B(B)); // Subtraction
    multiplication u_mul (.A(A), .B(B), .product_low(product_low), .product_high(product_high));  // Multiplication
    division u_div (.dividend(A), .divisor(B), .quotient(quotient_out), .remainder(remainder_out), .valid(valid_div)); // Division

    always @(*) begin
        // Default values (optional)
        product_low = 4'b0000;
        product_high = 4'b0000;
        valid_div = 1'b0;

        case (opcode[3:2])
            2'b00: begin    // Arithmetic operations (addition/subtraction)
                case (opcode[1:0])
                    2'b00: begin
                        Y = arithmetic_out;  // Addition
                        carry_out = add_carry_out;
                    end
                    2'b01: Y = arithmetic_out;  // Subtraction
                    default: Y = 4'b0000; // Default
                endcase
            end

            2'b01: begin  // Multiplication
                Y = product_low;  // Lower 4 bits of the product
                product_high = product_high;  // Returning upper 4 bits if needed
            end

            2'b10: begin  // Division
                Y = quotient_out;
                remainder = remainder_out;
                valid_div = 1'b1;
            end

            default: Y = 4'b0000; // Default case for unsupported operations
        endcase
    end
endmodule

`endif
`endif

Step3/shifter.v
`ifndef SHIFTER_V
`define SHIFTER_V

module shift_1bit (
    output reg [3:0] Y,     // Change Y to reg
    input [3:0] A,          // 4-bit input
    input [1:0] control     // 2-bit control signal for shift direction
);
    always @(*) begin
        case (control)
            2'b00: Y = A;               // No shift
            2'b01: Y = A << 1;          // Left shift by 1
            2'b10: Y = A >> 1;          // Right shift by 1
            default: Y = 4'b0000;       // Default case
        endcase
    end
endmodule

module shift_2x4bit (
    input [3:0] A,
    input [1:0] amt,     
    input dir,           
    output reg [3:0] Y   // Keep Y as reg since it's assigned in an always block
);

    always @(*) begin
        case (amt)
            2'b00: Y = A; // No shift
            2'b01: begin
                if (dir == 1'b0) // Left shift by 1
                    Y = {A[2:0], 1'b0};
                else // Right shift by 1
                    Y = {1'b0, A[3:1]};
            end
            2'b10: begin
                if (dir == 1'b0) // Left shift by 2
                    Y = {A[1:0], 2'b00};
                else // Right shift by 2
                    Y = {2'b00, A[3:2]};
            end
            default: Y = 4'b0000; // Default case (should not happen)
        endcase
    end

endmodule

`endif

Step3/logic_unit.v
`ifndef LOGIC_UNIT_V
`define LOGIC_UNIT_V

module nand_1bit (Y, A, B);
    output Y; 
    input A, B; 
    assign Y = !(A && B);
endmodule

module nor_1bit (Y, A, B);
    output Y; 
    input A, B;
    assign Y = !(A | B);
endmodule

module not_1bit (Y, A);
    output Y;
    input A;
    assign Y = !A; 
endmodule


module and_4bit (Y, A, B);
    output [3:0] Y;
    input [3:0] A, B;
    assign Y = A & B; 
endmodule

module nand_4bit (Y, A, B);
    output [3:0] Y;
    input [3:0] A, B; 

    assign Y = ~(A & B);  
endmodule

module nor_4bit (Y, A, B);
    output [3:0] Y;
    input [3:0] A, B;
    assign Y = ~(A | B); 
endmodule

module not_4bit (Y, A);
    output [3:0] Y;  // 4-bit output
    input  [3:0] A;  // 4-bit input
    assign Y = ~A; 
endmodule

module or_4bit (Y, A, B);
    output [3:0] Y;
    input [3:0] A, B;
    assign Y = A | B; 
endmodule

module xnor_4bit (Y, A, B);
    output [3:0] Y;  // 4-bit output
    input  [3:0] A;  // 4-bit input
    input  [3:0] B;  // 4-bit input
    assign Y = ~(A ^ B); 
endmodule

module xor_4bit (Y, A, B);
    output [3:0] Y; 
    input [3:0] A, B; 
    assign Y = A ^ B; 
endmodule

module logic_1bit (
    output reg Y,
    input A, B,           // Inputs
    input [2:0] control   // 3-bit control signal to select operation
);
    always @(*) begin
        case (control)
            3'b000: Y = A & B;        // AND
            3'b001: Y = !(A & B);     // NAND
            3'b010: Y = A | B;        // OR
            3'b011: Y = !(A | B);     // NOR
            3'b100: Y = A ^ B;        // XOR
            3'b101: Y = ~(A ^ B);     // XNOR
            3'b110: Y = !A;           // NOT
            default: Y = 0;           // Default to 0 if invalid control signal
        endcase
    end
endmodule

module logic_4bit (
    output reg [3:0] Y,      // 4-bit output
    input [3:0] A, B,        // 4-bit inputs
    input [2:0] control      // 3-bit control signal to select operation
);
    always @(*) begin
        case (control)
            3'b000: Y = A & B;        // AND
            3'b001: Y = ~(A & B);     // NAND
            3'b010: Y = A | B;        // OR
            3'b011: Y = ~(A | B);     // NOR
            3'b100: Y = A ^ B;        // XOR
            3'b101: Y = ~(A ^ B);     // XNOR
            3'b110: Y = ~A;           // NOT (applies to both A)
            default: Y = 4'b0000;     // Default to 0000 if invalid control signal
        endcase
    end
endmodule

`endif

Step3/testbench.v
`timescale 1ns / 1ps
`include "alu.v"
`include "logic_unit.v"
`include "shifter.v"

module testbench;

    // Inputs for logical operations
    reg A, B;
    reg [3:0] A4, B4;
    reg [1:0] amt;         // For shift amount
    reg dir;               // For shift direction (0 = left, 1 = right)
    reg [1:0] control;     // For controlling shift type (left/right)
    reg carry_in;          // For arithmetic operations
    reg [3:0] dividend, divisor;

    // Outputs for logical operations
    wire Y;           // 1-bit wire
    wire [3:0] Y4;    // 4-bit wire

    // Outputs for arithmetic operations
    wire [3:0] Sum, SubResult, MulLow, MulHigh, DivQuotient, DivRemainder;
    wire carry_out, valid;

    // Instantiate logical operations modules
    nand_1bit uut_nand1 (.Y(Y), .A(A), .B(B));
    nor_1bit uut_nor1 (.Y(Y), .A(A), .B(B));
    not_1bit uut_not1 (.Y(Y), .A(A));

    and_4bit uut_and4 (.Y(Y4), .A(A4), .B(B4));
    nand_4bit uut_nand4 (.Y(Y4), .A(A4), .B(B4));
    nor_4bit uut_nor4 (.Y(Y4), .A(A4), .B(B4));
    not_4bit uut_not4 (.Y(Y4), .A(A4));
    or_4bit uut_or4 (.Y(Y4), .A(A4), .B(B4));
    xor_4bit uut_xor4 (.Y(Y4), .A(A4), .B(B4));
    xnor_4bit uut_xnor4 (.Y(Y4), .A(A4), .B(B4));

    // Instantiate shift modules
    shift_1bit uut_shift1 (.Y(Y4), .A(A4));
    shift_2x4bit uut_shift4 (.Y(Y4), .A(A4), .amt(amt), .dir(dir));

    // Instantiate arithmetic operations modules
    addition uut_addition (.A(A4), .B(B4), .carry_in(carry_in), .Sum(Sum), .carry_out(carry_out));
    subtraction uut_subtraction (.Y(SubResult), .A(A4), .B(B4));
    multiplication uut_multiplication (.A(A4), .B(B4), .product_low(MulLow), .product_high(MulHigh));
    division uut_division (.dividend(dividend), .divisor(divisor), .quotient(DivQuotient), .remainder(DivRemainder), .valid(valid));

    // Create waveform dump
    initial begin
        $dumpfile("waveform.vcd");   // Name of the VCD file for the waveform
        $dumpvars(0, testbench);     // Dump all variables in the testbench module

        // Test Logical Operations
        A = 1; B = 0;
        #10; $display("nand_1bit: %b AND %b = %b", A, B, Y);
        #10; $display("nor_1bit: %b OR %b = %b", A, B, Y);
        #10; $display("not_1bit: NOT %b = %b", A, Y);

        A4 = 4'b1100; B4 = 4'b1010;
        #10; $display("and_4bit: %b AND %b = %b", A4, B4, Y4);
        #10; $display("nand_4bit: %b NAND %b = %b", A4, B4, Y4);
        #10; $display("nor_4bit: %b NOR %b = %b", A4, B4, Y4);
        #10; $display("not_4bit: NOT %b = %b", A4, Y4);
        #10; $display("or_4bit: %b OR %b = %b", A4, B4, Y4);
        #10; $display("xor_4bit: %b XOR %b = %b", A4, B4, Y4);
        #10; $display("xnor_4bit: %b XNOR %b = %b", A4, B4, Y4);

        // Test Shift Operations
        amt = 2'b01; dir = 1'b0; A4 = 4'b1010;   // Shift left by 1
        #10; $display("shift_1bit (left): %b -> %b", A4, Y4);

        amt = 2'b01; dir = 1'b1; A4 = 4'b1010;   // Shift right by 1
        #10; $display("shift_1bit (right): %b -> %b", A4, Y4);

        amt = 2'b10; dir = 1'b0; A4 = 4'b1010;   // Shift left by 2
        #10; $display("shift_2x4bit (left): %b -> %b", A4, Y4);

        amt = 2'b10; dir = 1'b1; A4 = 4'b1010;   // Shift right by 2
        #10; $display("shift_2x4bit (right): %b -> %b", A4, Y4);

        // Test Arithmetic Operations
        A4 = 4'b1101; B4 = 4'b1010; carry_in = 1'b0;
        #10; $display("addition: %b + %b = %b, carry_out = %b", A4, B4, Sum, carry_out);

        #10; $display("subtraction: %b - %b = %b", A4, B4, SubResult);

        #10; $display("multiplication: %b * %b = %b %b", A4, B4, MulHigh, MulLow);

        dividend = 4'b1010; divisor = 4'b0011; // 10 / 3
        #10; $display("division: %b / %b = quotient: %b, remainder: %b", dividend, divisor, DivQuotient, DivRemainder);

        $finish;
    end

endmodule

Step3/waveform.vcd
$date
	Mon Dec  2 12:09:23 2024
$end
$version
	Icarus Verilog
$end
$timescale
	1ps
$end
$scope module testbench $end
$var wire 1 ! Y $end
$var wire 4 " Y4 [3:0] $end
$var wire 1 # valid $end
$var wire 1 $ carry_out $end
$var wire 4 % Sum [3:0] $end
$var wire 4 & SubResult [3:0] $end
$var wire 4 ' MulLow [3:0] $end
$var wire 4 ( MulHigh [3:0] $end
$var wire 4 ) DivRemainder [3:0] $end
$var wire 4 * DivQuotient [3:0] $end
$var reg 1 + A $end
$var reg 4 , A4 [3:0] $end
$var reg 1 - B $end
$var reg 4 . B4 [3:0] $end
$var reg 2 / amt [1:0] $end
$var reg 1 0 carry_in $end
$var reg 1 1 dir $end
$var reg 4 2 dividend [3:0] $end
$var reg 4 3 divisor [3:0] $end
$scope module uut_addition $end
$var wire 4 4 A [3:0] $end
$var wire 4 5 B [3:0] $end
$var wire 1 0 carry_in $end
$var wire 5 6 full_sum [4:0] $end
$var wire 1 $ carry_out $end
$var wire 4 7 Sum [3:0] $end
$upscope $end
$scope module uut_and4 $end
$var wire 4 8 A [3:0] $end
$var wire 4 9 B [3:0] $end
$var wire 4 : Y [3:0] $end
$upscope $end
$scope module uut_division $end
$var wire 4 ; dividend [3:0] $end
$var wire 4 < divisor [3:0] $end
$var reg 4 = quotient [3:0] $end
$var reg 4 > remainder [3:0] $end
$var reg 4 ? temp_dividend [3:0] $end
$var reg 4 @ temp_quotient [3:0] $end
$var reg 1 # valid $end
$var integer 32 A i [31:0] $end
$upscope $end
$scope module uut_multiplication $end
$var wire 4 B A [3:0] $end
$var wire 4 C B [3:0] $end
$var wire 4 D product_low [3:0] $end
$var wire 4 E product_high [3:0] $end
$var wire 8 F full_product [7:0] $end
$upscope $end
$scope module uut_nand1 $end
$var wire 1 + A $end
$var wire 1 - B $end
$var wire 1 ! Y $end
$upscope $end
$scope module uut_nand4 $end
$var wire 4 G A [3:0] $end
$var wire 4 H B [3:0] $end
$var wire 4 I Y [3:0] $end
$upscope $end
$scope module uut_nor1 $end
$var wire 1 + A $end
$var wire 1 - B $end
$var wire 1 ! Y $end
$upscope $end
$scope module uut_nor4 $end
$var wire 4 J A [3:0] $end
$var wire 4 K B [3:0] $end
$var wire 4 L Y [3:0] $end
$upscope $end
$scope module uut_not1 $end
$var wire 1 + A $end
$var wire 1 ! Y $end
$upscope $end
$scope module uut_not4 $end
$var wire 4 M A [3:0] $end
$var wire 4 N Y [3:0] $end
$upscope $end
$scope module uut_or4 $end
$var wire 4 O A [3:0] $end
$var wire 4 P B [3:0] $end
$var wire 4 Q Y [3:0] $end
$upscope $end
$scope module uut_shift1 $end
$var wire 4 R A [3:0] $end
$var wire 2 S control [1:0] $end
$var reg 4 T Y [3:0] $end
$upscope $end
$scope module uut_shift4 $end
$var wire 4 U A [3:0] $end
$var wire 2 V amt [1:0] $end
$var wire 1 1 dir $end
$var reg 4 W Y [3:0] $end
$upscope $end
$scope module uut_subtraction $end
$var wire 4 X A [3:0] $end
$var wire 4 Y B [3:0] $end
$var wire 4 Z Y [3:0] $end
$upscope $end
$scope module uut_xnor4 $end
$var wire 4 [ A [3:0] $end
$var wire 4 \ B [3:0] $end
$var wire 4 ] Y [3:0] $end
$upscope $end
$scope module uut_xor4 $end
$var wire 4 ^ A [3:0] $end
$var wire 4 _ B [3:0] $end
$var wire 4 ` Y [3:0] $end
$upscope $end
$upscope $end
$enddefinitions $end
#0
$dumpvars
bx `
bx _
bx ^
bx ]
bx \
bx [
bx Z
bx Y
bx X
bx W
bx V
bx U
b0 T
bz S
bx R
bx Q
bx P
bx O
bx N
bx M
bx L
bx K
bx J
bx I
bx H
bx G
bx F
bx E
bx D
bx C
bx B
bx A
bx @
bx ?
bx >
bx =
bx <
bx ;
bx :
bx 9
bx 8
bx 7
bx 6
bx 5
bx 4
bx 3
bx 2
x1
x0
bx /
bx .
0-
bx ,
1+
bx *
bx )
bx (
bx '
bx &
bx %
x$
x#
bx "
x!
$end
#30000
b1000 '
b1000 D
b111 (
b111 E
b0 W
b1111000 F
b10 &
b10 Z
b1010 .
b1010 5
b1010 9
b1010 C
b1010 H
b1010 K
b1010 P
b1010 Y
b1010 \
b1010 _
b1100 ,
b1100 4
b1100 8
b1100 B
b1100 G
b1100 J
b1100 M
b1100 O
b1100 R
b1100 U
b1100 X
b1100 [
b1100 ^
#100000
b100 '
b100 D
b110 (
b110 E
b100 W
b1100100 F
b0 &
b0 Z
b1010 ,
b1010 4
b1010 8
b1010 B
b1010 G
b1010 J
b1010 M
b1010 O
b1010 R
b1010 U
b1010 X
b1010 [
b1010 ^
01
b1 /
b1 V
#110000
b101 W
11
#120000
b1000 W
01
b10 /
b10 V
#130000
b10 W
11
#140000
b111 %
b111 7
1$
b10 '
b10 D
b1000 (
b1000 E
b11 W
b10111 6
00
b10000010 F
b11 &
b11 Z
b1101 ,
b1101 4
b1101 8
b1101 B
b1101 G
b1101 J
b1101 M
b1101 O
b1101 R
b1101 U
b1101 X
b1101 [
b1101 ^
#170000
b11111111111111111111111111111111 A
b1010 @
b0 ?
1#
b1010 )
b1010 >
b1010 *
b1010 =
b11 3
b11 <
b1010 2
b1010 ;
