Step2/Xnor/xnor_gate_16bit.v
`ifndef xnor_gate_16bit_V
`define xnor_gate_16bit_V

module xnor_gate_16bit (Y, A, B);
    output [15:0] Y;  // 4-bit output
    input  [15:0] A;  // 4-bit input
    input  [15:0] B;  // 4-bit input
    assign Y = ~(A ^ B); 
endmodule

`endif

Step2/Xnor/xnor_tb_16bit.v
`timescale 1ns / 1ns
`include "xnor_gate_16bit.v"

module xnor_tb_16bit;

reg [15:0]A;
reg [15:0]B;
wire [15:0]Y;

xnor_gate_16bit uut(
    .Y(Y),
    .A(A),
    .B(B));

integer i;  // Loop variable
initial begin

    $dumpfile("xnor_tb_16bit.vcd");//holds output waveform
    $dumpvars(0, xnor_tb_16bit);
        // 16-bit Test Cases
        A = 16'h0000; B = 16'h0000; #10;
        A = 16'hFFFF; B = 16'hFFFF; #10;
        A = 16'hAAAA; B = 16'h5555; #10;
        A = 16'hF0F0; B = 16'hF0F0; #10;
        A = 16'h0F0F; B = 16'hF0F0; #10;
        A = 16'h3333; B = 16'h3333; #10;
        A = 16'h3C3C; B = 16'hC3C3; #10;
        A = 16'h1234; B = 16'h4321; #10;

    
    $display("Testing xnor 16 bit");

end

endmodule

Step2/Xnor/xnor_tb_16bit.vcd
$date
	Sun Oct 27 17:17:08 2024
$end
$version
	Icarus Verilog
$end
$timescale
	1ns
$end
$scope module xnor_tb_16bit $end
$var wire 16 ! Y [15:0] $end
$var reg 16 " A [15:0] $end
$var reg 16 # B [15:0] $end
$scope module uut $end
$var wire 16 $ A [15:0] $end
$var wire 16 % B [15:0] $end
$var wire 16 & Y [15:0] $end
$upscope $end
$upscope $end
$enddefinitions $end
$comment Show the parameter values. $end
$dumpall
$end
#0
$dumpvars
b1111111111111111 &
b0 %
b0 $
b0 #
b0 "
b1111111111111111 !
$end
#10
b1111111111111111 #
b1111111111111111 %
b1111111111111111 "
b1111111111111111 $
#20
b0 !
b0 &
b101010101010101 #
b101010101010101 %
b1010101010101010 "
b1010101010101010 $
#30
b1111111111111111 !
b1111111111111111 &
b1111000011110000 #
b1111000011110000 %
b1111000011110000 "
b1111000011110000 $
#40
b0 !
b0 &
b111100001111 "
b111100001111 $
#50
b1111111111111111 !
b1111111111111111 &
b11001100110011 #
b11001100110011 %
b11001100110011 "
b11001100110011 $
#60
b0 !
b0 &
b1100001111000011 #
b1100001111000011 %
b11110000111100 "
b11110000111100 $
#70
b1010111011101010 !
b1010111011101010 &
b100001100100001 #
b100001100100001 %
b1001000110100 "
b1001000110100 $
