Step2/Xnor/xnor_gate_32bit.v
`ifndef xnor_GATE_32bit_V
`define xnor_GATE_32bit_V

module xnor_gate_32bit (Y, A, B);
    output [31:0] Y;  // 4-bit output
    input  [31:0] A;  // 4-bit input
    input  [31:0] B;  // 4-bit input
    assign Y = ~(A ^ B); 
endmodule

`endif

Step2/Xnor/xnor_tb_32bit.v
`timescale 1ns / 1ns
`include "xnor_gate_32bit.v"

module xnor_tb_32bit;

reg [31:0]A;
reg [31:0]B;
wire [31:0]Y;

xnor_gate_32bit uut(
    .Y(Y),
    .A(A),
    .B(B));

integer i;  // Loop variable
initial begin

    $dumpfile("xnor_tb_32bit.vcd");//holds output waveform
    $dumpvars(0, xnor_tb_32bit);
        A = 32'h00000000; B = 32'h00000000; #10;
        A = 32'hFFFFFFFF; B = 32'hFFFFFFFF; #10;
        A = 32'hAAAAAAAA; B = 32'h55555555; #10;
        A = 32'hF0F0F0F0; B = 32'hF0F0F0F0; #10;
        A = 32'h0F0F0F0F; B = 32'hF0F0F0F0; #10;
        A = 32'h33333333; B = 32'h33333333; #10;
        A = 32'h3C3C3C3C; B = 32'hC3C3C3C3; #10;
        A = 32'h12345678; B = 32'h87654321; #10;

    
    $display("Testing xnor");

end

endmodule

Step2/Xnor/xnor_tb_32bit.vcd
$date
	Sun Oct 27 17:17:56 2024
$end
$version
	Icarus Verilog
$end
$timescale
	1ns
$end
$scope module xnor_tb_32bit $end
$var wire 32 ! Y [31:0] $end
$var reg 32 " A [31:0] $end
$var reg 32 # B [31:0] $end
$scope module uut $end
$var wire 32 $ A [31:0] $end
$var wire 32 % B [31:0] $end
$var wire 32 & Y [31:0] $end
$upscope $end
$upscope $end
$enddefinitions $end
$comment Show the parameter values. $end
$dumpall
$end
#0
$dumpvars
b11111111111111111111111111111111 &
b0 %
b0 $
b0 #
b0 "
b11111111111111111111111111111111 !
$end
#10
b11111111111111111111111111111111 #
b11111111111111111111111111111111 %
b11111111111111111111111111111111 "
b11111111111111111111111111111111 $
#20
b0 !
b0 &
b1010101010101010101010101010101 #
b1010101010101010101010101010101 %
b10101010101010101010101010101010 "
b10101010101010101010101010101010 $
#30
b11111111111111111111111111111111 !
b11111111111111111111111111111111 &
b11110000111100001111000011110000 #
b11110000111100001111000011110000 %
b11110000111100001111000011110000 "
b11110000111100001111000011110000 $
#40
b0 !
b0 &
b1111000011110000111100001111 "
b1111000011110000111100001111 $
#50
b11111111111111111111111111111111 !
b11111111111111111111111111111111 &
b110011001100110011001100110011 #
b110011001100110011001100110011 %
b110011001100110011001100110011 "
b110011001100110011001100110011 $
#60
b0 !
b0 &
b11000011110000111100001111000011 #
b11000011110000111100001111000011 %
b111100001111000011110000111100 "
b111100001111000011110000111100 $
#70
b1101010101011101110101010100110 !
b1101010101011101110101010100110 &
b10000111011001010100001100100001 #
b10000111011001010100001100100001 %
b10010001101000101011001111000 "
b10010001101000101011001111000 $
