Step2/Xnor/xnor_gate.v
`ifndef xnor_GATE_V
`define xnor_GATE_V

module xnor_gate (Y, A, B);
    output [3:0] Y;  // 4-bit output
    input  [3:0] A;  // 4-bit input
    input  [3:0] B;  // 4-bit input
    assign Y = ~(A ^ B); 
endmodule

`endif

Step2/Xnor/xnor_tb.v
`timescale 1ns / 1ns
`include "xnor_gate.v"

module xnor_tb;

reg [3:0]A;
reg [3:0]B;
wire [3:0]Y;

xnor_gate uut(
    .Y(Y),
    .A(A),
    .B(B));

integer i;  // Loop variable
initial begin

    $dumpfile("xnor_tb.vcd");//holds output waveform
    $dumpvars(0, xnor_tb);
        // Apply test cases
        A = 4'b0000; B = 4'b0000; #10; 
        A = 4'b0000; B = 4'b1111; #10; 
        A = 4'b1010; B = 4'b0101; #10; 
        A = 4'b1100; B = 4'b1010; #10; 
        A = 4'b1111; B = 4'b1111; #10; 
        A = 4'b0110; B = 4'b0110; #10; 
        A = 4'b1001; B = 4'b1001; #10; 
        A = 4'b1101; B = 4'b0111; #10;

    
    $display("Testing xnor");

end

endmodule

Step2/Xnor/xnor_tb.vcd
$date
	Mon Oct 28 15:11:45 2024
$end
$version
	Icarus Verilog
$end
$timescale
	1ns
$end
$scope module xnor_tb $end
$var wire 4 ! Y [3:0] $end
$var reg 4 " A [3:0] $end
$var reg 4 # B [3:0] $end
$scope module uut $end
$var wire 4 $ A [3:0] $end
$var wire 4 % B [3:0] $end
$var wire 4 & Y [3:0] $end
$upscope $end
$upscope $end
$enddefinitions $end
$comment Show the parameter values. $end
$dumpall
$end
#0
$dumpvars
b1111 &
b0 %
b0 $
b0 #
b0 "
b1111 !
$end
#10
b0 !
b0 &
b1111 #
b1111 %
#20
b101 #
b101 %
b1010 "
b1010 $
#30
b1001 !
b1001 &
b1010 #
b1010 %
b1100 "
b1100 $
#40
b1111 !
b1111 &
b1111 #
b1111 %
b1111 "
b1111 $
#50
b110 #
b110 %
b110 "
b110 $
#60
b1001 #
b1001 %
b1001 "
b1001 $
#70
b101 !
b101 &
b111 #
b111 %
b1101 "
b1101 $
