Step2/Xnor/xnor_gate_8bit.v
`ifndef xnor_GATE_8bit_V
`define xnor_GATE_8bit_V

module xnor_gate_8bit (Y, A, B);
    output [7:0] Y;  // 4-bit output
    input  [7:0] A;  // 4-bit input
    input  [7:0] B;  // 4-bit input
    assign Y = ~(A ^ B); 
endmodule

`endif

Step2/Xnor/xnor_tb_8bit.v
`timescale 1ns / 1ns
`include "xnor_gate_8bit.v"

module xnor_tb_8bit;

reg [7:0]A;
reg [7:0]B;
wire [7:0]Y;

xnor_gate_8bit uut(
    .Y(Y),
    .A(A),
    .B(B));

integer i;  // Loop variable
initial begin

    $dumpfile("xnor_tb_8bit.vcd");//holds output waveform
    $dumpvars(0, xnor_tb_8bit);
        // Apply test cases
        A = 8'h00; B = 8'h00; #10;
        A = 8'hFF; B = 8'hFF; #10;
        A = 8'hAA; B = 8'h55; #10;
        A = 8'hF0; B = 8'hF0; #10;
        A = 8'h0F; B = 8'hF0; #10;
        A = 8'h33; B = 8'h33; #10;
        A = 8'h3C; B = 8'hC3; #10;
        A = 8'h12; B = 8'h21; #10;

    
    $display("Testing xnor");

end

endmodule

Step2/Xnor/xnor_tb_8bit.vcd
$date
	Sun Oct 27 17:16:22 2024
$end
$version
	Icarus Verilog
$end
$timescale
	1ns
$end
$scope module xnor_tb_8bit $end
$var wire 8 ! Y [7:0] $end
$var reg 8 " A [7:0] $end
$var reg 8 # B [7:0] $end
$scope module uut $end
$var wire 8 $ A [7:0] $end
$var wire 8 % B [7:0] $end
$var wire 8 & Y [7:0] $end
$upscope $end
$upscope $end
$enddefinitions $end
$comment Show the parameter values. $end
$dumpall
$end
#0
$dumpvars
b11111111 &
b0 %
b0 $
b0 #
b0 "
b11111111 !
$end
#10
b11111111 #
b11111111 %
b11111111 "
b11111111 $
#20
b0 !
b0 &
b1010101 #
b1010101 %
b10101010 "
b10101010 $
#30
b11111111 !
b11111111 &
b11110000 #
b11110000 %
b11110000 "
b11110000 $
#40
b0 !
b0 &
b1111 "
b1111 $
#50
b11111111 !
b11111111 &
b110011 #
b110011 %
b110011 "
b110011 $
#60
b0 !
b0 &
b11000011 #
b11000011 %
b111100 "
b111100 $
#70
b11001100 !
b11001100 &
b100001 #
b100001 %
b10010 "
b10010 $
