Step2/And/and_gate.v
`ifndef AND_GATE_V
`define AND_GATE_V

module and_gate (Y, A, B);
    output [3:0] Y;     // 4-bit output
    input [3:0] A, B;   // 4-bit inputs
    assign Y = A & B;   // Bitwise AND operation
endmodule

`endif

Step2/And/and_tb.v
`timescale 1ns / 1ns
`include "and_gate.v"

module and_tb;

    reg [3:0] A, B;  // 4-bit inputs
    wire [3:0] Y;    // 4-bit output

    and_gate uut(Y, A, B);  // Instantiate the 4-bit AND gate

    integer i, j;

    initial begin
        $dumpfile("and_tb.vcd");  // holds output waveform
        $dumpvars(0, and_tb);

        // Loop through all 16 possible values of A and B
        for (i = 0; i < 16; i = i + 1) begin
            for (j = 0; j < 16; j = j + 1) begin
                A = i;  // Assign A to the current value
                B = j;  // Assign B to the current value
                #10;    // Wait for 10 time units
                $display("A = %b, B = %b, Y = %b", A, B, Y);  // Display A, B, and Y
            end
        end

        $display("All combinations tested");
        $finish;
    end

endmodule

Step2/And/and_tb.vcd
$date
	Sun Oct 27 10:17:14 2024
$end
$version
	Icarus Verilog
$end
$timescale
	1ns
$end
$scope module and_tb $end
$var wire 4 ! Y [3:0] $end
$var reg 4 " A [3:0] $end
$var reg 4 # B [3:0] $end
$var integer 32 $ i [31:0] $end
$var integer 32 % j [31:0] $end
$scope module uut $end
$var wire 4 & A [3:0] $end
$var wire 4 ' B [3:0] $end
$var wire 4 ( Y [3:0] $end
$upscope $end
$upscope $end
$enddefinitions $end
#0
$dumpvars
b0 (
b0 '
b0 &
b0 %
b0 $
b0 #
b0 "
b0 !
$end
#10
b1 #
b1 '
b1 %
#20
b10 #
b10 '
b10 %
#30
b11 #
b11 '
b11 %
#40
b100 #
b100 '
b100 %
#50
b101 #
b101 '
b101 %
#60
b110 #
b110 '
b110 %
#70
b111 #
b111 '
b111 %
#80
b1000 #
b1000 '
b1000 %
#90
b1001 #
b1001 '
b1001 %
#100
b1010 #
b1010 '
b1010 %
#110
b1011 #
b1011 '
b1011 %
#120
b1100 #
b1100 '
b1100 %
#130
b1101 #
b1101 '
b1101 %
#140
b1110 #
b1110 '
b1110 %
#150
b1111 #
b1111 '
b1111 %
#160
b0 #
b0 '
b1 "
b1 &
b1 $
b0 %
#170
b1 !
b1 (
b1 #
b1 '
b1 %
#180
b0 !
b0 (
b10 #
b10 '
b10 %
#190
b1 !
b1 (
b11 #
b11 '
b11 %
#200
b0 !
b0 (
b100 #
b100 '
b100 %
#210
b1 !
b1 (
b101 #
b101 '
b101 %
#220
b0 !
b0 (
b110 #
b110 '
b110 %
#230
b1 !
b1 (
b111 #
b111 '
b111 %
#240
b0 !
b0 (
b1000 #
b1000 '
b1000 %
#250
b1 !
b1 (
b1001 #
b1001 '
b1001 %
#260
b0 !
b0 (
b1010 #
b1010 '
b1010 %
#270
b1 !
b1 (
b1011 #
b1011 '
b1011 %
#280
b0 !
b0 (
b1100 #
b1100 '
b1100 %
#290
b1 !
b1 (
b1101 #
b1101 '
b1101 %
#300
b0 !
b0 (
b1110 #
b1110 '
b1110 %
#310
b1 !
b1 (
b1111 #
b1111 '
b1111 %
#320
b0 !
b0 (
b0 #
b0 '
b10 "
b10 &
b10 $
b0 %
#330
b1 #
b1 '
b1 %
#340
b10 !
b10 (
b10 #
b10 '
b10 %
#350
b11 #
b11 '
b11 %
#360
b0 !
b0 (
b100 #
b100 '
b100 %
#370
b101 #
b101 '
b101 %
#380
b10 !
b10 (
b110 #
b110 '
b110 %
#390
b111 #
b111 '
b111 %
#400
b0 !
b0 (
b1000 #
b1000 '
b1000 %
#410
b1001 #
b1001 '
b1001 %
#420
b10 !
b10 (
b1010 #
b1010 '
b1010 %
#430
b1011 #
b1011 '
b1011 %
#440
b0 !
b0 (
b1100 #
b1100 '
b1100 %
#450
b1101 #
b1101 '
b1101 %
#460
b10 !
b10 (
b1110 #
b1110 '
b1110 %
#470
b1111 #
b1111 '
b1111 %
#480
b0 !
b0 (
b0 #
b0 '
b11 "
b11 &
b11 $
b0 %
#490
b1 !
b1 (
b1 #
b1 '
b1 %
#500
b10 !
b10 (
b10 #
b10 '
b10 %
#510
b11 !
b11 (
b11 #
b11 '
b11 %
#520
b0 !
b0 (
b100 #
b100 '
b100 %
#530
b1 !
b1 (
b101 #
b101 '
b101 %
#540
b10 !
b10 (
b110 #
b110 '
b110 %
#550
b11 !
b11 (
b111 #
b111 '
b111 %
#560
b0 !
b0 (
b1000 #
b1000 '
b1000 %
#570
b1 !
b1 (
b1001 #
b1001 '
b1001 %
#580
b10 !
b10 (
b1010 #
b1010 '
b1010 %
#590
b11 !
b11 (
b1011 #
b1011 '
b1011 %
#600
b0 !
b0 (
b1100 #
b1100 '
b1100 %
#610
b1 !
b1 (
b1101 #
b1101 '
b1101 %
#620
b10 !
b10 (
b1110 #
b1110 '
b1110 %
#630
b11 !
b11 (
b1111 #
b1111 '
b1111 %
#640
b0 !
b0 (
b0 #
b0 '
b100 "
b100 &
b100 $
b0 %
#650
b1 #
b1 '
b1 %
#660
b10 #
b10 '
b10 %
#670
b11 #
b11 '
b11 %
#680
b100 !
b100 (
b100 #
b100 '
b100 %
#690
b101 #
b101 '
b101 %
#700
b110 #
b110 '
b110 %
#710
b111 #
b111 '
b111 %
#720
b0 !
b0 (
b1000 #
b1000 '
b1000 %
#730
b1001 #
b1001 '
b1001 %
#740
b1010 #
b1010 '
b1010 %
#750
b1011 #
b1011 '
b1011 %
#760
b100 !
b100 (
b1100 #
b1100 '
b1100 %
#770
b1101 #
b1101 '
b1101 %
#780
b1110 #
b1110 '
b1110 %
#790
b1111 #
b1111 '
b1111 %
#800
b0 !
b0 (
b0 #
b0 '
b101 "
b101 &
b101 $
b0 %
#810
b1 !
b1 (
b1 #
b1 '
b1 %
#820
b0 !
b0 (
b10 #
b10 '
b10 %
#830
b1 !
b1 (
b11 #
b11 '
b11 %
#840
b100 !
b100 (
b100 #
b100 '
b100 %
#850
b101 !
b101 (
b101 #
b101 '
b101 %
#860
b100 !
b100 (
b110 #
b110 '
b110 %
#870
b101 !
b101 (
b111 #
b111 '
b111 %
#880
b0 !
b0 (
b1000 #
b1000 '
b1000 %
#890
b1 !
b1 (
b1001 #
b1001 '
b1001 %
#900
b0 !
b0 (
b1010 #
b1010 '
b1010 %
#910
b1 !
b1 (
b1011 #
b1011 '
b1011 %
#920
b100 !
b100 (
b1100 #
b1100 '
b1100 %
#930
b101 !
b101 (
b1101 #
b1101 '
b1101 %
#940
b100 !
b100 (
b1110 #
b1110 '
b1110 %
#950
b101 !
b101 (
b1111 #
b1111 '
b1111 %
#960
b0 !
b0 (
b0 #
b0 '
b110 "
b110 &
b110 $
b0 %
#970
b1 #
b1 '
b1 %
#980
b10 !
b10 (
b10 #
b10 '
b10 %
#990
b11 #
b11 '
b11 %
#1000
b100 !
b100 (
b100 #
b100 '
b100 %
#1010
b101 #
b101 '
b101 %
#1020
b110 !
b110 (
b110 #
b110 '
b110 %
#1030
b111 #
b111 '
b111 %
#1040
b0 !
b0 (
b1000 #
b1000 '
b1000 %
#1050
b1001 #
b1001 '
b1001 %
#1060
b10 !
b10 (
b1010 #
b1010 '
b1010 %
#1070
b1011 #
b1011 '
b1011 %
#1080
b100 !
b100 (
b1100 #
b1100 '
b1100 %
#1090
b1101 #
b1101 '
b1101 %
#1100
b110 !
b110 (
b1110 #
b1110 '
b1110 %
#1110
b1111 #
b1111 '
b1111 %
#1120
b0 !
b0 (
b0 #
b0 '
b111 "
b111 &
b111 $
b0 %
#1130
b1 !
b1 (
b1 #
b1 '
b1 %
#1140
b10 !
b10 (
b10 #
b10 '
b10 %
#1150
b11 !
b11 (
b11 #
b11 '
b11 %
#1160
b100 !
b100 (
b100 #
b100 '
b100 %
#1170
b101 !
b101 (
b101 #
b101 '
b101 %
#1180
b110 !
b110 (
b110 #
b110 '
b110 %
#1190
b111 !
b111 (
b111 #
b111 '
b111 %
#1200
b0 !
b0 (
b1000 #
b1000 '
b1000 %
#1210
b1 !
b1 (
b1001 #
b1001 '
b1001 %
#1220
b10 !
b10 (
b1010 #
b1010 '
b1010 %
#1230
b11 !
b11 (
b1011 #
b1011 '
b1011 %
#1240
b100 !
b100 (
b1100 #
b1100 '
b1100 %
#1250
b101 !
b101 (
b1101 #
b1101 '
b1101 %
#1260
b110 !
b110 (
b1110 #
b1110 '
b1110 %
#1270
b111 !
b111 (
b1111 #
b1111 '
b1111 %
#1280
b0 !
b0 (
b0 #
b0 '
b1000 "
b1000 &
b1000 $
b0 %
#1290
b1 #
b1 '
b1 %
#1300
b10 #
b10 '
b10 %
#1310
b11 #
b11 '
b11 %
#1320
b100 #
b100 '
b100 %
#1330
b101 #
b101 '
b101 %
#1340
b110 #
b110 '
b110 %
#1350
b111 #
b111 '
b111 %
#1360
b1000 !
b1000 (
b1000 #
b1000 '
b1000 %
#1370
b1001 #
b1001 '
b1001 %
#1380
b1010 #
b1010 '
b1010 %
#1390
b1011 #
b1011 '
b1011 %
#1400
b1100 #
b1100 '
b1100 %
#1410
b1101 #
b1101 '
b1101 %
#1420
b1110 #
b1110 '
b1110 %
#1430
b1111 #
b1111 '
b1111 %
#1440
b0 !
b0 (
b0 #
b0 '
b1001 "
b1001 &
b1001 $
b0 %
#1450
b1 !
b1 (
b1 #
b1 '
b1 %
#1460
b0 !
b0 (
b10 #
b10 '
b10 %
#1470
b1 !
b1 (
b11 #
b11 '
b11 %
#1480
b0 !
b0 (
b100 #
b100 '
b100 %
#1490
b1 !
b1 (
b101 #
b101 '
b101 %
#1500
b0 !
b0 (
b110 #
b110 '
b110 %
#1510
b1 !
b1 (
b111 #
b111 '
b111 %
#1520
b1000 !
b1000 (
b1000 #
b1000 '
b1000 %
#1530
b1001 !
b1001 (
b1001 #
b1001 '
b1001 %
#1540
b1000 !
b1000 (
b1010 #
b1010 '
b1010 %
#1550
b1001 !
b1001 (
b1011 #
b1011 '
b1011 %
#1560
b1000 !
b1000 (
b1100 #
b1100 '
b1100 %
#1570
b1001 !
b1001 (
b1101 #
b1101 '
b1101 %
#1580
b1000 !
b1000 (
b1110 #
b1110 '
b1110 %
#1590
b1001 !
b1001 (
b1111 #
b1111 '
b1111 %
#1600
b0 !
b0 (
b0 #
b0 '
b1010 "
b1010 &
b1010 $
b0 %
#1610
b1 #
b1 '
b1 %
#1620
b10 !
b10 (
b10 #
b10 '
b10 %
#1630
b11 #
b11 '
b11 %
#1640
b0 !
b0 (
b100 #
b100 '
b100 %
#1650
b101 #
b101 '
b101 %
#1660
b10 !
b10 (
b110 #
b110 '
b110 %
#1670
b111 #
b111 '
b111 %
#1680
b1000 !
b1000 (
b1000 #
b1000 '
b1000 %
#1690
b1001 #
b1001 '
b1001 %
#1700
b1010 !
b1010 (
b1010 #
b1010 '
b1010 %
#1710
b1011 #
b1011 '
b1011 %
#1720
b1000 !
b1000 (
b1100 #
b1100 '
b1100 %
#1730
b1101 #
b1101 '
b1101 %
#1740
b1010 !
b1010 (
b1110 #
b1110 '
b1110 %
#1750
b1111 #
b1111 '
b1111 %
#1760
b0 !
b0 (
b0 #
b0 '
b1011 "
b1011 &
b1011 $
b0 %
#1770
b1 !
b1 (
b1 #
b1 '
b1 %
#1780
b10 !
b10 (
b10 #
b10 '
b10 %
#1790
b11 !
b11 (
b11 #
b11 '
b11 %
#1800
b0 !
b0 (
b100 #
b100 '
b100 %
#1810
b1 !
b1 (
b101 #
b101 '
b101 %
#1820
b10 !
b10 (
b110 #
b110 '
b110 %
#1830
b11 !
b11 (
b111 #
b111 '
b111 %
#1840
b1000 !
b1000 (
b1000 #
b1000 '
b1000 %
#1850
b1001 !
b1001 (
b1001 #
b1001 '
b1001 %
#1860
b1010 !
b1010 (
b1010 #
b1010 '
b1010 %
#1870
b1011 !
b1011 (
b1011 #
b1011 '
b1011 %
#1880
b1000 !
b1000 (
b1100 #
b1100 '
b1100 %
#1890
b1001 !
b1001 (
b1101 #
b1101 '
b1101 %
#1900
b1010 !
b1010 (
b1110 #
b1110 '
b1110 %
#1910
b1011 !
b1011 (
b1111 #
b1111 '
b1111 %
#1920
b0 !
b0 (
b0 #
b0 '
b1100 "
b1100 &
b1100 $
b0 %
#1930
b1 #
b1 '
b1 %
#1940
b10 #
b10 '
b10 %
#1950
b11 #
b11 '
b11 %
#1960
b100 !
b100 (
b100 #
b100 '
b100 %
#1970
b101 #
b101 '
b101 %
#1980
b110 #
b110 '
b110 %
#1990
b111 #
b111 '
b111 %
#2000
b1000 !
b1000 (
b1000 #
b1000 '
b1000 %
#2010
b1001 #
b1001 '
b1001 %
#2020
b1010 #
b1010 '
b1010 %
#2030
b1011 #
b1011 '
b1011 %
#2040
b1100 !
b1100 (
b1100 #
b1100 '
b1100 %
#2050
b1101 #
b1101 '
b1101 %
#2060
b1110 #
b1110 '
b1110 %
#2070
b1111 #
b1111 '
b1111 %
#2080
b0 !
b0 (
b0 #
b0 '
b1101 "
b1101 &
b1101 $
b0 %
#2090
b1 !
b1 (
b1 #
b1 '
b1 %
#2100
b0 !
b0 (
b10 #
b10 '
b10 %
#2110
b1 !
b1 (
b11 #
b11 '
b11 %
#2120
b100 !
b100 (
b100 #
b100 '
b100 %
#2130
b101 !
b101 (
b101 #
b101 '
b101 %
#2140
b100 !
b100 (
b110 #
b110 '
b110 %
#2150
b101 !
b101 (
b111 #
b111 '
b111 %
#2160
b1000 !
b1000 (
b1000 #
b1000 '
b1000 %
#2170
b1001 !
b1001 (
b1001 #
b1001 '
b1001 %
#2180
b1000 !
b1000 (
b1010 #
b1010 '
b1010 %
#2190
b1001 !
b1001 (
b1011 #
b1011 '
b1011 %
#2200
b1100 !
b1100 (
b1100 #
b1100 '
b1100 %
#2210
b1101 !
b1101 (
b1101 #
b1101 '
b1101 %
#2220
b1100 !
b1100 (
b1110 #
b1110 '
b1110 %
#2230
b1101 !
b1101 (
b1111 #
b1111 '
b1111 %
#2240
b0 !
b0 (
b0 #
b0 '
b1110 "
b1110 &
b1110 $
b0 %
#2250
b1 #
b1 '
b1 %
#2260
b10 !
b10 (
b10 #
b10 '
b10 %
#2270
b11 #
b11 '
b11 %
#2280
b100 !
b100 (
b100 #
b100 '
b100 %
#2290
b101 #
b101 '
b101 %
#2300
b110 !
b110 (
b110 #
b110 '
b110 %
#2310
b111 #
b111 '
b111 %
#2320
b1000 !
b1000 (
b1000 #
b1000 '
b1000 %
#2330
b1001 #
b1001 '
b1001 %
#2340
b1010 !
b1010 (
b1010 #
b1010 '
b1010 %
#2350
b1011 #
b1011 '
b1011 %
#2360
b1100 !
b1100 (
b1100 #
b1100 '
b1100 %
#2370
b1101 #
b1101 '
b1101 %
#2380
b1110 !
b1110 (
b1110 #
b1110 '
b1110 %
#2390
b1111 #
b1111 '
b1111 %
#2400
b0 !
b0 (
b0 #
b0 '
b1111 "
b1111 &
b1111 $
b0 %
#2410
b1 !
b1 (
b1 #
b1 '
b1 %
#2420
b10 !
b10 (
b10 #
b10 '
b10 %
#2430
b11 !
b11 (
b11 #
b11 '
b11 %
#2440
b100 !
b100 (
b100 #
b100 '
b100 %
#2450
b101 !
b101 (
b101 #
b101 '
b101 %
#2460
b110 !
b110 (
b110 #
b110 '
b110 %
#2470
b111 !
b111 (
b111 #
b111 '
b111 %
#2480
b1000 !
b1000 (
b1000 #
b1000 '
b1000 %
#2490
b1001 !
b1001 (
b1001 #
b1001 '
b1001 %
#2500
b1010 !
b1010 (
b1010 #
b1010 '
b1010 %
#2510
b1011 !
b1011 (
b1011 #
b1011 '
b1011 %
#2520
b1100 !
b1100 (
b1100 #
b1100 '
b1100 %
#2530
b1101 !
b1101 (
b1101 #
b1101 '
b1101 %
#2540
b1110 !
b1110 (
b1110 #
b1110 '
b1110 %
#2550
b1111 !
b1111 (
b1111 #
b1111 '
b1111 %
#2560
b10000 $
b10000 %
