Step2/Xor/xor_gate.v
`ifndef XOR_GATE_V
`define XOR_GATE_V

module xor_gate (Y, A, B);
    output [3:0] Y; 
    input [3:0] A, B; 
    assign Y = A ^ B; 
endmodule

`endif

Step2/Xor/xor_tb.v
`timescale 1ns / 1ns
`include "xor_gate.v"

module xor_tb;

    reg [3:0] A, B; 
    wire [3:0] Y; 

    xor_gate uut(Y, A, B);

    integer i, j;

    initial begin
        $dumpfile("xor_tb.vcd"); 
        $dumpvars(0, xor_tb);

        // Loop through all 16 possible values of A and B
        for (i = 0; i < 16; i = i + 1) begin
            for (j = 0; j < 16; j = j + 1) begin
                A = i;
                B = j; 
                #10;
                $display("A = %b, B = %b, Y = %b", A, B, Y);  // Display A, B, and Y
            end
        end

        $display("All combinations tested");
        $finish;
    end

endmodule

Step2/Xor/xor_tb.vcd
$date
	Sun Oct 27 10:24:57 2024
$end
$version
	Icarus Verilog
$end
$timescale
	1ns
$end
$scope module xor_tb $end
$var wire 4 ! Y [3:0] $end
$var reg 4 " A [3:0] $end
$var reg 4 # B [3:0] $end
$var integer 32 $ i [31:0] $end
$var integer 32 % j [31:0] $end
$scope module uut $end
$var wire 4 & A [3:0] $end
$var wire 4 ' B [3:0] $end
$var wire 4 ( Y [3:0] $end
$upscope $end
$upscope $end
$enddefinitions $end
#0
$dumpvars
b0 (
b0 '
b0 &
b0 %
b0 $
b0 #
b0 "
b0 !
$end
#10
b1 !
b1 (
b1 #
b1 '
b1 %
#20
b10 !
b10 (
b10 #
b10 '
b10 %
#30
b11 !
b11 (
b11 #
b11 '
b11 %
#40
b100 !
b100 (
b100 #
b100 '
b100 %
#50
b101 !
b101 (
b101 #
b101 '
b101 %
#60
b110 !
b110 (
b110 #
b110 '
b110 %
#70
b111 !
b111 (
b111 #
b111 '
b111 %
#80
b1000 !
b1000 (
b1000 #
b1000 '
b1000 %
#90
b1001 !
b1001 (
b1001 #
b1001 '
b1001 %
#100
b1010 !
b1010 (
b1010 #
b1010 '
b1010 %
#110
b1011 !
b1011 (
b1011 #
b1011 '
b1011 %
#120
b1100 !
b1100 (
b1100 #
b1100 '
b1100 %
#130
b1101 !
b1101 (
b1101 #
b1101 '
b1101 %
#140
b1110 !
b1110 (
b1110 #
b1110 '
b1110 %
#150
b1111 !
b1111 (
b1111 #
b1111 '
b1111 %
#160
b1 !
b1 (
b0 #
b0 '
b1 "
b1 &
b1 $
b0 %
#170
b0 !
b0 (
b1 #
b1 '
b1 %
#180
b11 !
b11 (
b10 #
b10 '
b10 %
#190
b10 !
b10 (
b11 #
b11 '
b11 %
#200
b101 !
b101 (
b100 #
b100 '
b100 %
#210
b100 !
b100 (
b101 #
b101 '
b101 %
#220
b111 !
b111 (
b110 #
b110 '
b110 %
#230
b110 !
b110 (
b111 #
b111 '
b111 %
#240
b1001 !
b1001 (
b1000 #
b1000 '
b1000 %
#250
b1000 !
b1000 (
b1001 #
b1001 '
b1001 %
#260
b1011 !
b1011 (
b1010 #
b1010 '
b1010 %
#270
b1010 !
b1010 (
b1011 #
b1011 '
b1011 %
#280
b1101 !
b1101 (
b1100 #
b1100 '
b1100 %
#290
b1100 !
b1100 (
b1101 #
b1101 '
b1101 %
#300
b1111 !
b1111 (
b1110 #
b1110 '
b1110 %
#310
b1110 !
b1110 (
b1111 #
b1111 '
b1111 %
#320
b10 !
b10 (
b0 #
b0 '
b10 "
b10 &
b10 $
b0 %
#330
b11 !
b11 (
b1 #
b1 '
b1 %
#340
b0 !
b0 (
b10 #
b10 '
b10 %
#350
b1 !
b1 (
b11 #
b11 '
b11 %
#360
b110 !
b110 (
b100 #
b100 '
b100 %
#370
b111 !
b111 (
b101 #
b101 '
b101 %
#380
b100 !
b100 (
b110 #
b110 '
b110 %
#390
b101 !
b101 (
b111 #
b111 '
b111 %
#400
b1010 !
b1010 (
b1000 #
b1000 '
b1000 %
#410
b1011 !
b1011 (
b1001 #
b1001 '
b1001 %
#420
b1000 !
b1000 (
b1010 #
b1010 '
b1010 %
#430
b1001 !
b1001 (
b1011 #
b1011 '
b1011 %
#440
b1110 !
b1110 (
b1100 #
b1100 '
b1100 %
#450
b1111 !
b1111 (
b1101 #
b1101 '
b1101 %
#460
b1100 !
b1100 (
b1110 #
b1110 '
b1110 %
#470
b1101 !
b1101 (
b1111 #
b1111 '
b1111 %
#480
b11 !
b11 (
b0 #
b0 '
b11 "
b11 &
b11 $
b0 %
#490
b10 !
b10 (
b1 #
b1 '
b1 %
#500
b1 !
b1 (
b10 #
b10 '
b10 %
#510
b0 !
b0 (
b11 #
b11 '
b11 %
#520
b111 !
b111 (
b100 #
b100 '
b100 %
#530
b110 !
b110 (
b101 #
b101 '
b101 %
#540
b101 !
b101 (
b110 #
b110 '
b110 %
#550
b100 !
b100 (
b111 #
b111 '
b111 %
#560
b1011 !
b1011 (
b1000 #
b1000 '
b1000 %
#570
b1010 !
b1010 (
b1001 #
b1001 '
b1001 %
#580
b1001 !
b1001 (
b1010 #
b1010 '
b1010 %
#590
b1000 !
b1000 (
b1011 #
b1011 '
b1011 %
#600
b1111 !
b1111 (
b1100 #
b1100 '
b1100 %
#610
b1110 !
b1110 (
b1101 #
b1101 '
b1101 %
#620
b1101 !
b1101 (
b1110 #
b1110 '
b1110 %
#630
b1100 !
b1100 (
b1111 #
b1111 '
b1111 %
#640
b100 !
b100 (
b0 #
b0 '
b100 "
b100 &
b100 $
b0 %
#650
b101 !
b101 (
b1 #
b1 '
b1 %
#660
b110 !
b110 (
b10 #
b10 '
b10 %
#670
b111 !
b111 (
b11 #
b11 '
b11 %
#680
b0 !
b0 (
b100 #
b100 '
b100 %
#690
b1 !
b1 (
b101 #
b101 '
b101 %
#700
b10 !
b10 (
b110 #
b110 '
b110 %
#710
b11 !
b11 (
b111 #
b111 '
b111 %
#720
b1100 !
b1100 (
b1000 #
b1000 '
b1000 %
#730
b1101 !
b1101 (
b1001 #
b1001 '
b1001 %
#740
b1110 !
b1110 (
b1010 #
b1010 '
b1010 %
#750
b1111 !
b1111 (
b1011 #
b1011 '
b1011 %
#760
b1000 !
b1000 (
b1100 #
b1100 '
b1100 %
#770
b1001 !
b1001 (
b1101 #
b1101 '
b1101 %
#780
b1010 !
b1010 (
b1110 #
b1110 '
b1110 %
#790
b1011 !
b1011 (
b1111 #
b1111 '
b1111 %
#800
b101 !
b101 (
b0 #
b0 '
b101 "
b101 &
b101 $
b0 %
#810
b100 !
b100 (
b1 #
b1 '
b1 %
#820
b111 !
b111 (
b10 #
b10 '
b10 %
#830
b110 !
b110 (
b11 #
b11 '
b11 %
#840
b1 !
b1 (
b100 #
b100 '
b100 %
#850
b0 !
b0 (
b101 #
b101 '
b101 %
#860
b11 !
b11 (
b110 #
b110 '
b110 %
#870
b10 !
b10 (
b111 #
b111 '
b111 %
#880
b1101 !
b1101 (
b1000 #
b1000 '
b1000 %
#890
b1100 !
b1100 (
b1001 #
b1001 '
b1001 %
#900
b1111 !
b1111 (
b1010 #
b1010 '
b1010 %
#910
b1110 !
b1110 (
b1011 #
b1011 '
b1011 %
#920
b1001 !
b1001 (
b1100 #
b1100 '
b1100 %
#930
b1000 !
b1000 (
b1101 #
b1101 '
b1101 %
#940
b1011 !
b1011 (
b1110 #
b1110 '
b1110 %
#950
b1010 !
b1010 (
b1111 #
b1111 '
b1111 %
#960
b110 !
b110 (
b0 #
b0 '
b110 "
b110 &
b110 $
b0 %
#970
b111 !
b111 (
b1 #
b1 '
b1 %
#980
b100 !
b100 (
b10 #
b10 '
b10 %
#990
b101 !
b101 (
b11 #
b11 '
b11 %
#1000
b10 !
b10 (
b100 #
b100 '
b100 %
#1010
b11 !
b11 (
b101 #
b101 '
b101 %
#1020
b0 !
b0 (
b110 #
b110 '
b110 %
#1030
b1 !
b1 (
b111 #
b111 '
b111 %
#1040
b1110 !
b1110 (
b1000 #
b1000 '
b1000 %
#1050
b1111 !
b1111 (
b1001 #
b1001 '
b1001 %
#1060
b1100 !
b1100 (
b1010 #
b1010 '
b1010 %
#1070
b1101 !
b1101 (
b1011 #
b1011 '
b1011 %
#1080
b1010 !
b1010 (
b1100 #
b1100 '
b1100 %
#1090
b1011 !
b1011 (
b1101 #
b1101 '
b1101 %
#1100
b1000 !
b1000 (
b1110 #
b1110 '
b1110 %
#1110
b1001 !
b1001 (
b1111 #
b1111 '
b1111 %
#1120
b111 !
b111 (
b0 #
b0 '
b111 "
b111 &
b111 $
b0 %
#1130
b110 !
b110 (
b1 #
b1 '
b1 %
#1140
b101 !
b101 (
b10 #
b10 '
b10 %
#1150
b100 !
b100 (
b11 #
b11 '
b11 %
#1160
b11 !
b11 (
b100 #
b100 '
b100 %
#1170
b10 !
b10 (
b101 #
b101 '
b101 %
#1180
b1 !
b1 (
b110 #
b110 '
b110 %
#1190
b0 !
b0 (
b111 #
b111 '
b111 %
#1200
b1111 !
b1111 (
b1000 #
b1000 '
b1000 %
#1210
b1110 !
b1110 (
b1001 #
b1001 '
b1001 %
#1220
b1101 !
b1101 (
b1010 #
b1010 '
b1010 %
#1230
b1100 !
b1100 (
b1011 #
b1011 '
b1011 %
#1240
b1011 !
b1011 (
b1100 #
b1100 '
b1100 %
#1250
b1010 !
b1010 (
b1101 #
b1101 '
b1101 %
#1260
b1001 !
b1001 (
b1110 #
b1110 '
b1110 %
#1270
b1000 !
b1000 (
b1111 #
b1111 '
b1111 %
#1280
b0 #
b0 '
b1000 "
b1000 &
b1000 $
b0 %
#1290
b1001 !
b1001 (
b1 #
b1 '
b1 %
#1300
b1010 !
b1010 (
b10 #
b10 '
b10 %
#1310
b1011 !
b1011 (
b11 #
b11 '
b11 %
#1320
b1100 !
b1100 (
b100 #
b100 '
b100 %
#1330
b1101 !
b1101 (
b101 #
b101 '
b101 %
#1340
b1110 !
b1110 (
b110 #
b110 '
b110 %
#1350
b1111 !
b1111 (
b111 #
b111 '
b111 %
#1360
b0 !
b0 (
b1000 #
b1000 '
b1000 %
#1370
b1 !
b1 (
b1001 #
b1001 '
b1001 %
#1380
b10 !
b10 (
b1010 #
b1010 '
b1010 %
#1390
b11 !
b11 (
b1011 #
b1011 '
b1011 %
#1400
b100 !
b100 (
b1100 #
b1100 '
b1100 %
#1410
b101 !
b101 (
b1101 #
b1101 '
b1101 %
#1420
b110 !
b110 (
b1110 #
b1110 '
b1110 %
#1430
b111 !
b111 (
b1111 #
b1111 '
b1111 %
#1440
b1001 !
b1001 (
b0 #
b0 '
b1001 "
b1001 &
b1001 $
b0 %
#1450
b1000 !
b1000 (
b1 #
b1 '
b1 %
#1460
b1011 !
b1011 (
b10 #
b10 '
b10 %
#1470
b1010 !
b1010 (
b11 #
b11 '
b11 %
#1480
b1101 !
b1101 (
b100 #
b100 '
b100 %
#1490
b1100 !
b1100 (
b101 #
b101 '
b101 %
#1500
b1111 !
b1111 (
b110 #
b110 '
b110 %
#1510
b1110 !
b1110 (
b111 #
b111 '
b111 %
#1520
b1 !
b1 (
b1000 #
b1000 '
b1000 %
#1530
b0 !
b0 (
b1001 #
b1001 '
b1001 %
#1540
b11 !
b11 (
b1010 #
b1010 '
b1010 %
#1550
b10 !
b10 (
b1011 #
b1011 '
b1011 %
#1560
b101 !
b101 (
b1100 #
b1100 '
b1100 %
#1570
b100 !
b100 (
b1101 #
b1101 '
b1101 %
#1580
b111 !
b111 (
b1110 #
b1110 '
b1110 %
#1590
b110 !
b110 (
b1111 #
b1111 '
b1111 %
#1600
b1010 !
b1010 (
b0 #
b0 '
b1010 "
b1010 &
b1010 $
b0 %
#1610
b1011 !
b1011 (
b1 #
b1 '
b1 %
#1620
b1000 !
b1000 (
b10 #
b10 '
b10 %
#1630
b1001 !
b1001 (
b11 #
b11 '
b11 %
#1640
b1110 !
b1110 (
b100 #
b100 '
b100 %
#1650
b1111 !
b1111 (
b101 #
b101 '
b101 %
#1660
b1100 !
b1100 (
b110 #
b110 '
b110 %
#1670
b1101 !
b1101 (
b111 #
b111 '
b111 %
#1680
b10 !
b10 (
b1000 #
b1000 '
b1000 %
#1690
b11 !
b11 (
b1001 #
b1001 '
b1001 %
#1700
b0 !
b0 (
b1010 #
b1010 '
b1010 %
#1710
b1 !
b1 (
b1011 #
b1011 '
b1011 %
#1720
b110 !
b110 (
b1100 #
b1100 '
b1100 %
#1730
b111 !
b111 (
b1101 #
b1101 '
b1101 %
#1740
b100 !
b100 (
b1110 #
b1110 '
b1110 %
#1750
b101 !
b101 (
b1111 #
b1111 '
b1111 %
#1760
b1011 !
b1011 (
b0 #
b0 '
b1011 "
b1011 &
b1011 $
b0 %
#1770
b1010 !
b1010 (
b1 #
b1 '
b1 %
#1780
b1001 !
b1001 (
b10 #
b10 '
b10 %
#1790
b1000 !
b1000 (
b11 #
b11 '
b11 %
#1800
b1111 !
b1111 (
b100 #
b100 '
b100 %
#1810
b1110 !
b1110 (
b101 #
b101 '
b101 %
#1820
b1101 !
b1101 (
b110 #
b110 '
b110 %
#1830
b1100 !
b1100 (
b111 #
b111 '
b111 %
#1840
b11 !
b11 (
b1000 #
b1000 '
b1000 %
#1850
b10 !
b10 (
b1001 #
b1001 '
b1001 %
#1860
b1 !
b1 (
b1010 #
b1010 '
b1010 %
#1870
b0 !
b0 (
b1011 #
b1011 '
b1011 %
#1880
b111 !
b111 (
b1100 #
b1100 '
b1100 %
#1890
b110 !
b110 (
b1101 #
b1101 '
b1101 %
#1900
b101 !
b101 (
b1110 #
b1110 '
b1110 %
#1910
b100 !
b100 (
b1111 #
b1111 '
b1111 %
#1920
b1100 !
b1100 (
b0 #
b0 '
b1100 "
b1100 &
b1100 $
b0 %
#1930
b1101 !
b1101 (
b1 #
b1 '
b1 %
#1940
b1110 !
b1110 (
b10 #
b10 '
b10 %
#1950
b1111 !
b1111 (
b11 #
b11 '
b11 %
#1960
b1000 !
b1000 (
b100 #
b100 '
b100 %
#1970
b1001 !
b1001 (
b101 #
b101 '
b101 %
#1980
b1010 !
b1010 (
b110 #
b110 '
b110 %
#1990
b1011 !
b1011 (
b111 #
b111 '
b111 %
#2000
b100 !
b100 (
b1000 #
b1000 '
b1000 %
#2010
b101 !
b101 (
b1001 #
b1001 '
b1001 %
#2020
b110 !
b110 (
b1010 #
b1010 '
b1010 %
#2030
b111 !
b111 (
b1011 #
b1011 '
b1011 %
#2040
b0 !
b0 (
b1100 #
b1100 '
b1100 %
#2050
b1 !
b1 (
b1101 #
b1101 '
b1101 %
#2060
b10 !
b10 (
b1110 #
b1110 '
b1110 %
#2070
b11 !
b11 (
b1111 #
b1111 '
b1111 %
#2080
b1101 !
b1101 (
b0 #
b0 '
b1101 "
b1101 &
b1101 $
b0 %
#2090
b1100 !
b1100 (
b1 #
b1 '
b1 %
#2100
b1111 !
b1111 (
b10 #
b10 '
b10 %
#2110
b1110 !
b1110 (
b11 #
b11 '
b11 %
#2120
b1001 !
b1001 (
b100 #
b100 '
b100 %
#2130
b1000 !
b1000 (
b101 #
b101 '
b101 %
#2140
b1011 !
b1011 (
b110 #
b110 '
b110 %
#2150
b1010 !
b1010 (
b111 #
b111 '
b111 %
#2160
b101 !
b101 (
b1000 #
b1000 '
b1000 %
#2170
b100 !
b100 (
b1001 #
b1001 '
b1001 %
#2180
b111 !
b111 (
b1010 #
b1010 '
b1010 %
#2190
b110 !
b110 (
b1011 #
b1011 '
b1011 %
#2200
b1 !
b1 (
b1100 #
b1100 '
b1100 %
#2210
b0 !
b0 (
b1101 #
b1101 '
b1101 %
#2220
b11 !
b11 (
b1110 #
b1110 '
b1110 %
#2230
b10 !
b10 (
b1111 #
b1111 '
b1111 %
#2240
b1110 !
b1110 (
b0 #
b0 '
b1110 "
b1110 &
b1110 $
b0 %
#2250
b1111 !
b1111 (
b1 #
b1 '
b1 %
#2260
b1100 !
b1100 (
b10 #
b10 '
b10 %
#2270
b1101 !
b1101 (
b11 #
b11 '
b11 %
#2280
b1010 !
b1010 (
b100 #
b100 '
b100 %
#2290
b1011 !
b1011 (
b101 #
b101 '
b101 %
#2300
b1000 !
b1000 (
b110 #
b110 '
b110 %
#2310
b1001 !
b1001 (
b111 #
b111 '
b111 %
#2320
b110 !
b110 (
b1000 #
b1000 '
b1000 %
#2330
b111 !
b111 (
b1001 #
b1001 '
b1001 %
#2340
b100 !
b100 (
b1010 #
b1010 '
b1010 %
#2350
b101 !
b101 (
b1011 #
b1011 '
b1011 %
#2360
b10 !
b10 (
b1100 #
b1100 '
b1100 %
#2370
b11 !
b11 (
b1101 #
b1101 '
b1101 %
#2380
b0 !
b0 (
b1110 #
b1110 '
b1110 %
#2390
b1 !
b1 (
b1111 #
b1111 '
b1111 %
#2400
b1111 !
b1111 (
b0 #
b0 '
b1111 "
b1111 &
b1111 $
b0 %
#2410
b1110 !
b1110 (
b1 #
b1 '
b1 %
#2420
b1101 !
b1101 (
b10 #
b10 '
b10 %
#2430
b1100 !
b1100 (
b11 #
b11 '
b11 %
#2440
b1011 !
b1011 (
b100 #
b100 '
b100 %
#2450
b1010 !
b1010 (
b101 #
b101 '
b101 %
#2460
b1001 !
b1001 (
b110 #
b110 '
b110 %
#2470
b1000 !
b1000 (
b111 #
b111 '
b111 %
#2480
b111 !
b111 (
b1000 #
b1000 '
b1000 %
#2490
b110 !
b110 (
b1001 #
b1001 '
b1001 %
#2500
b101 !
b101 (
b1010 #
b1010 '
b1010 %
#2510
b100 !
b100 (
b1011 #
b1011 '
b1011 %
#2520
b11 !
b11 (
b1100 #
b1100 '
b1100 %
#2530
b10 !
b10 (
b1101 #
b1101 '
b1101 %
#2540
b1 !
b1 (
b1110 #
b1110 '
b1110 %
#2550
b0 !
b0 (
b1111 #
b1111 '
b1111 %
#2560
b10000 $
b10000 %
